LICENSE.txt
MANIFEST.in
README.md
setup.py
nautobot_evpn/__init__.py
nautobot_evpn/filters.py
nautobot_evpn/forms.py
nautobot_evpn/helper.py
nautobot_evpn/models.py
nautobot_evpn/navigation.py
nautobot_evpn/tables.py
nautobot_evpn/template_content.py
nautobot_evpn/urls.py
nautobot_evpn/utilities.py
nautobot_evpn/views.py
nautobot_evpn.egg-info/PKG-INFO
nautobot_evpn.egg-info/SOURCES.txt
nautobot_evpn.egg-info/dependency_links.txt
nautobot_evpn.egg-info/not-zip-safe
nautobot_evpn.egg-info/requires.txt
nautobot_evpn.egg-info/top_level.txt
nautobot_evpn/api/__init__.py
nautobot_evpn/api/filters.py
nautobot_evpn/api/serializers.py
nautobot_evpn/api/urls.py
nautobot_evpn/api/views.py
nautobot_evpn/migrations/0001_initial.py
nautobot_evpn/migrations/0002_auto_20220901_1053.py
nautobot_evpn/migrations/0003_rename_vlanvrf_vrfprimaryvlan.py
nautobot_evpn/migrations/0004_auto_20220901_1406.py
nautobot_evpn/migrations/0005_alter_ethernetsegment_name.py
nautobot_evpn/migrations/0006_auto_20221214_1803.py
nautobot_evpn/migrations/0007_auto_20221215_1510.py
nautobot_evpn/migrations/0008_auto_20230131_1111.py
nautobot_evpn/migrations/0009_auto_20240221_0931.py
nautobot_evpn/migrations/__init__.py
nautobot_evpn/templates/nautobot_evpn/anycastip_form.html
nautobot_evpn/templates/nautobot_evpn/ethernetsegment.html
nautobot_evpn/templates/nautobot_evpn/ethernetsegment_list.html
nautobot_evpn/templates/nautobot_evpn/ethernetsegmentmembership_form.html
nautobot_evpn/templates/nautobot_evpn/vlanvrf_form.html
nautobot_evpn/templates/nautobot_evpn/vrfprimaryvlan_form.html
nautobot_evpn/templates/nautobot_evpn/inc/interface_buttons.html
nautobot_evpn/templates/nautobot_evpn/inc/interface_es_widget.html
nautobot_evpn/templates/nautobot_evpn/inc/svi_widget.html
nautobot_evpn/templates/nautobot_evpn/inc/vlan_buttons.html
nautobot_evpn/templates/nautobot_evpn/inc/vrf_buttons.html