Metadata-Version: 2.1
Name: nautobot-evpn
Version: 1.0.0
Summary: A Nautobot plugin for evpn management
Home-page: https://gitlab-ce.gwdg.de/gwdg-netz/nautobot-plugins/nautobot-evpn
Author: Gesellschaft für wissenschaftliche Datenverarbeitung mbH Göttingen
Author-email: netzadmin@gwdg.de
License: Apache-2.0
Platform: UNKNOWN
License-File: LICENSE.txt
